{
    "fluentMethods": true,
    "clientRootFolder": "",
    "relationships": [],
    "fields": [
        {
            "fieldName": "tipo",
            "fieldType": "TipoLogradouro",
            "fieldValues": "RUA,AVENIDA,TRAVESSA,QUADRA,BECO,ESTRADA,CHACARA,RODOVIA,VIADUTO,SITIO,FEIRA,SETOR,MORRO,LARGO,FAZENDA"
        },
        {
            "fieldName": "nome",
            "fieldType": "String"
        }
    ],
    "changelogDate": "20190512012221",
    "dto": "no",
    "searchEngine": false,
    "service": "serviceImpl",
    "entityTableName": "logradouro",
    "databaseType": "sql",
    "jpaMetamodelFiltering": false,
    "pagination": "pagination"
}
